taiga_plugin_iframe/__init__.py
taiga_plugin_iframe/api.py
taiga_plugin_iframe/apps.py
taiga_plugin_iframe/models.py
taiga_plugin_iframe/permissions.py
taiga_plugin_iframe/serializers.py
taiga_plugin_iframe/tests.py
taiga_plugin_iframe/views.py
taiga_plugin_iframe/migrations/0001_initial.py
taiga_plugin_iframe/migrations/__init__.py
taiga_plugin_iframe-0.0.1.dist-info/DESCRIPTION.rst
taiga_plugin_iframe-0.0.1.dist-info/METADATA
taiga_plugin_iframe-0.0.1.dist-info/RECORD
taiga_plugin_iframe-0.0.1.dist-info/WHEEL
taiga_plugin_iframe-0.0.1.dist-info/metadata.json
taiga_plugin_iframe-0.0.1.dist-info/top_level.txt
