Metadata-Version: 2.0
Name: taiga-plugin-iframe
Version: 0.0.1
Summary: The Taiga plugin for custom iframe with menu icons
Home-page: https://github.com/msiniy/taiga-plugin-iframe
Author: Max Sinelnikov
Author-email: msiniy@gmail.com
License: AGPL
Keywords: taiga,iframe,menu,plugin
Platform: UNKNOWN
Classifier: Programming Language :: Python
Classifier: Development Status :: 3 - Alpha
Classifier: Framework :: Django
Classifier: Intended Audience :: Developers
Classifier: License :: OSI Approved :: GNU Affero General Public License v3
Classifier: Operating System :: OS Independent
Classifier: Topic :: Internet :: WWW/HTTP
Requires-Dist: django (>=1.8.5)
